{
  "capturedAt": "2026-07-09T09:54:08+0300",
  "method": "host-side IO proxies for paths timed by app perf diagnostics; not full UI startup. Use Console filter metadata.kind=perf for in-app timings after launch.",
  "profiles": {
    "small": {
      "label": "notes (small workspace)",
      "rootNormalized": "/users/alexeyperov/documents/notes",
      "fsRoot": "/Users/alexeyperov/Documents/notes",
      "openTabs": 18,
      "openDocuments": 21,
      "workspaceFilesApprox": 17,
      "workspaceSizeMB": 0.0,
      "fullWalkMs": 0.717,
      "projectTreeRootLoadProxy": {
        "rootEntryCount": 15,
        "samplesMs": [
          0.043,
          0.026,
          0.029,
          0.023,
          0.023,
          0.022,
          0.025
        ],
        "p50Ms": 0.025,
        "p95Ms": 0.029
      },
      "tabActivationStatProxy": {
        "existingFileCount": 13,
        "documentCount": 21,
        "samplesMs": [
          0.053,
          0.055,
          0.056,
          0.045,
          0.047,
          0.051,
          0.053
        ],
        "p50Ms": 0.053,
        "p95Ms": 0.055
      },
      "windowSessionSnapshotBytes": 58080
    },
    "large": {
      "label": "unity-ai-hub (large workspace)",
      "rootNormalized": "/users/alexeyperov/projects/unity-ai-hub",
      "fsRoot": "/Users/alexeyperov/Projects/Unity-AI-Hub",
      "openTabs": 4,
      "openDocuments": 4,
      "workspaceFilesApprox": 7966,
      "workspaceSizeMB": 336.4,
      "fullWalkMs": 122.69,
      "projectTreeRootLoadProxy": {
        "rootEntryCount": 17,
        "samplesMs": [
          0.033,
          0.019,
          0.018,
          0.017,
          0.017,
          0.02,
          0.017
        ],
        "p50Ms": 0.018,
        "p95Ms": 0.02
      },
      "tabActivationStatProxy": {
        "existingFileCount": 3,
        "documentCount": 4,
        "samplesMs": [
          0.017,
          0.014,
          0.011,
          0.011,
          0.011,
          0.011,
          0.015
        ],
        "p50Ms": 0.011,
        "p95Ms": 0.015
      },
      "windowSessionSnapshotBytes": 60248
    }
  },
  "sessionHydrationSerialProxy": {
    "small_2": {
      "threadCount": 2,
      "totalBytes": 8489,
      "samplesMs": [
        0.146,
        0.108,
        0.1,
        0.102,
        0.2,
        0.148,
        0.097
      ],
      "p50Ms": 0.108,
      "p95Ms": 0.148
    },
    "medium_10": {
      "threadCount": 10,
      "totalBytes": 38023,
      "samplesMs": [
        0.428,
        0.367,
        0.349,
        0.348,
        0.345,
        0.338,
        0.34
      ],
      "p50Ms": 0.348,
      "p95Ms": 0.367
    },
    "large_40": {
      "threadCount": 40,
      "totalBytes": 147758,
      "samplesMs": [
        1.441,
        1.404,
        1.312,
        1.297,
        1.401,
        1.356,
        1.364
      ],
      "p50Ms": 1.364,
      "p95Ms": 1.404
    },
    "large_40_inflated_8kb": {
      "threadCount": 40,
      "totalBytes": 468398,
      "samplesMs": [
        1.79,
        1.759,
        1.748,
        1.877,
        1.835,
        1.653,
        1.63
      ],
      "p50Ms": 1.759,
      "p95Ms": 1.835
    }
  },
  "howToReproduceInApp": [
    "Launch SpecOps with Console open (or plugin log).",
    "Filter diagnostics where metadata.kind === 'perf'.",
    "Cold start on small workspace (notes) and large workspace (unity-ai-hub); record startup.total and startup.phase.*",
    "Switch between the two workspaces; record workspace.switchRestore / workspace.restore / workspace.sessionLoad.",
    "Switch file tabs; record tab.activationSideEffects and projectTree.rootLoad (should not re-root-load on tab-only churn after P3)."
  ]
}
